{"kind":"Notebook","sha256":"432bb663e3a89a632e774e4589529597edf937afd12881175ce8074b662a261c","slug":"hw","location":"/homework/01_hw.ipynb","dependencies":[],"frontmatter":{"title":"Homework 1","subtitle":"The topic of the homework","date":"2019-06-19T00:00:00.000Z","exports":[{"format":"ipynb","filename":"01_hw.ipynb","url":"/build/01_hw-0e5d1196dc2d7495a25ac5289f06009e.ipynb"},{"format":"pdf","filename":"hw1_cunningham.pdf","url":"/build/hw1_cunningham-bc84afa5bf2ae9b14fa649e0efeaed52.pdf"}],"downloads":[{"title":"PDF","url":"/build/hw1_cunningham-bc84afa5bf2ae9b14fa649e0efeaed52.pdf","filename":"hw1_cunningham.pdf","format":"pdf","static":true},{"title":"Jupyter Notebook","url":"/build/01_hw-0e5d1196dc2d7495a25ac5289f06009e.ipynb","filename":"01_hw.ipynb","static":true}],"kernelspec":{"name":"python3","language":"python","display_name":"Python 3 (ipykernel)"},"authors":[{"nameParsed":{"literal":"Jacob Cunningham","given":"Jacob","family":"Cunningham"},"name":"Jacob Cunningham","corresponding":true,"email":"jjc132@pitt.edu","affiliations":["pitt"],"github":"jacob-cunningham-ds","id":"contributors-Users\\jjcun\\Documents\\ece_2390\\main\\myst-generated-uid-0"}],"open_access":true,"license":{"content":{"id":"CC-BY-4.0","name":"Creative Commons Attribution 4.0 International","free":true,"CC":true,"url":"https://creativecommons.org/licenses/by/4.0/"}},"github":"https://github.com/jacob-cunningham-ds/ece_2390","subject":"Image Processing and Computer Vision","affiliations":[{"id":"pitt","name":"University of Pittsburgh","department":"Mechanical Engineering"}]},"mdast":{"type":"root","children":[{"type":"block","data":{"part":"abstract"},"visibility":"remove","children":[{"type":"paragraph","position":{"start":{"line":1,"column":1},"end":{"line":1,"column":1}},"children":[{"type":"text","value":"This article contains problem prompts, calculations, and results from homework 1 for ECE 2390.","position":{"start":{"line":1,"column":1},"end":{"line":1,"column":1}},"key":"sEnSGkcA5W"}],"key":"InI9lqahnA"}],"key":"Ob7A5DVZSI"},{"type":"block","kind":"notebook-content","data":{"editable":true,"slideshow":{"slide_type":""},"tags":[]},"children":[{"type":"paragraph","position":{"start":{"line":1,"column":1},"end":{"line":1,"column":1}},"children":[{"type":"text","value":"Preamble to the exercises goes here.","position":{"start":{"line":1,"column":1},"end":{"line":1,"column":1}},"key":"ffHP9n1CJ3"}],"key":"T0cnUbrOVA"}],"visibility":"show","key":"CjpPwhj2cj"},{"type":"block","kind":"notebook-content","data":{},"children":[{"type":"heading","depth":2,"position":{"start":{"line":1,"column":1},"end":{"line":1,"column":1}},"children":[{"type":"text","value":"Exercise 1","position":{"start":{"line":1,"column":1},"end":{"line":1,"column":1}},"key":"hUnIyRsadH"}],"identifier":"exercise-1","label":"Exercise 1","html_id":"exercise-1","implicit":true,"key":"nXJZyZheUs"}],"key":"Q2KVdqGCEp"},{"type":"block","kind":"notebook-content","data":{},"children":[{"type":"paragraph","position":{"start":{"line":1,"column":1},"end":{"line":1,"column":1}},"children":[{"type":"text","value":"Pick a function and plot it.","position":{"start":{"line":1,"column":1},"end":{"line":1,"column":1}},"key":"dkuD4QWZti"}],"key":"mzvuccphas"}],"key":"ONZY0oxfSK"},{"type":"block","kind":"notebook-code","data":{"editable":true,"jupyter":{"source_hidden":true},"slideshow":{"slide_type":""},"tags":[]},"children":[{"type":"code","lang":"python","executable":true,"value":"import numpy as np\nimport matplotlib.pyplot as plt\n\nx = np.linspace(-2 * np.pi, 2 * np.pi, 1000)\ny = np.sin(x)\n\n\nplt.plot(x, y, label='sin(x)')\nplt.plot(x, np.cos(x), label='cos(x)')\nplt.legend()\nplt.ylabel('y')\nplt.xlabel('x')\nplt.title('y vs. x')\nplt.ylim([-2, 2])\nplt.xlim([-2 * np.pi, 2 * np.pi])\nplt.grid()\nplt.show()","identifier":"code-1-code","enumerator":"1","html_id":"code-1-code","visibility":"show","key":"KKrsgADHL8"},{"type":"output","id":"tI3DJL6-G3z8ytg4yRyiG","data":[{"output_type":"display_data","metadata":{},"data":{"image/png":{"content_type":"image/png","hash":"a586163c20a752392c2f562d290f445b","path":"/build/a586163c20a752392c2f562d290f445b.png"},"text/plain":{"content":"<Figure size 640x480 with 1 Axes>","content_type":"text/plain"}}}],"identifier":"code-1-output","html_id":"code-1-output","visibility":"show","key":"McbWWB2R02"}],"identifier":"code-1","label":"code-1","html_id":"code-1","visibility":"show","key":"B3dnnS02Tn"},{"type":"block","kind":"notebook-content","data":{"editable":true,"slideshow":{"slide_type":""},"tags":[]},"children":[{"type":"heading","depth":2,"position":{"start":{"line":1,"column":1},"end":{"line":1,"column":1}},"children":[{"type":"text","value":"Exercise 2","position":{"start":{"line":1,"column":1},"end":{"line":1,"column":1}},"key":"cqgCposp2p"}],"identifier":"exercise-2","label":"Exercise 2","html_id":"exercise-2","implicit":true,"key":"JdP82IjlvZ"}],"visibility":"show","key":"J9fKzR3xGg"},{"type":"block","kind":"notebook-content","data":{},"children":[{"type":"paragraph","position":{"start":{"line":1,"column":1},"end":{"line":1,"column":1}},"children":[{"type":"text","value":"Show the function as a Data Frame.","position":{"start":{"line":1,"column":1},"end":{"line":1,"column":1}},"key":"kZVofTCsr8"}],"key":"CucBTcgYyR"}],"key":"iiuPN7JfBV"},{"type":"block","kind":"notebook-code","data":{"editable":true,"slideshow":{"slide_type":""},"tags":[]},"children":[{"type":"code","lang":"python","executable":true,"value":"import pandas as pd\n\nmat = np.column_stack((x, y))\n\ndf = pd.DataFrame(mat, columns = ['x', 'y'])\n\ndf.head()","identifier":"code-ex2-code","enumerator":"2","html_id":"code-ex2-code","visibility":"show","key":"sTnSj4qXNC"},{"type":"output","id":"OnGMVz4quo5a2ugCflQ75","data":[{"output_type":"execute_result","execution_count":15,"metadata":{},"data":{"text/html":{"content":"<div>\n<style scoped>\n    .dataframe tbody tr th:only-of-type {\n        vertical-align: middle;\n    }\n\n    .dataframe tbody tr th {\n        vertical-align: top;\n    }\n\n    .dataframe thead th {\n        text-align: right;\n    }\n</style>\n<table border=\"1\" class=\"dataframe\">\n  <thead>\n    <tr style=\"text-align: right;\">\n      <th></th>\n      <th>x</th>\n      <th>y</th>\n    </tr>\n  </thead>\n  <tbody>\n    <tr>\n      <th>0</th>\n      <td>-6.283185</td>\n      <td>2.449294e-16</td>\n    </tr>\n    <tr>\n      <th>1</th>\n      <td>-6.026729</td>\n      <td>2.536546e-01</td>\n    </tr>\n    <tr>\n      <th>2</th>\n      <td>-5.770272</td>\n      <td>4.907176e-01</td>\n    </tr>\n    <tr>\n      <th>3</th>\n      <td>-5.513816</td>\n      <td>6.956826e-01</td>\n    </tr>\n    <tr>\n      <th>4</th>\n      <td>-5.257359</td>\n      <td>8.551428e-01</td>\n    </tr>\n  </tbody>\n</table>\n</div>","content_type":"text/html"},"text/plain":{"content":"          x             y\n0 -6.283185  2.449294e-16\n1 -6.026729  2.536546e-01\n2 -5.770272  4.907176e-01\n3 -5.513816  6.956826e-01\n4 -5.257359  8.551428e-01","content_type":"text/plain"}}}],"identifier":"code-ex2-output","html_id":"code-ex2-output","visibility":"show","key":"iES8MDM20f"}],"identifier":"code-ex2","label":"code-ex2","html_id":"code-ex2","visibility":"show","key":"kvnkkKv2S6"}],"key":"KnOHY91nZT"},"references":{"cite":{"order":[],"data":{}}},"footer":{"navigation":{"prev":{"title":"Lecture 1","url":"/lecture","group":"Notes"}}},"domain":"http://localhost:3000"}